cool_booy_tmux/__init__.py
cool_booy_tmux/config.py
cool_booy_tmux/main.py
cool_booy_tmux/my_tmux_config.py
cool_booy_tmux/utils.py
cool_booy_tmux/version.py
cool_booy_tmux-1.1.1.dist-info/LICENSE
cool_booy_tmux-1.1.1.dist-info/METADATA
cool_booy_tmux-1.1.1.dist-info/WHEEL
cool_booy_tmux-1.1.1.dist-info/entry_points.txt
cool_booy_tmux-1.1.1.dist-info/top_level.txt
cool_booy_tmux-1.1.1.dist-info/RECORD
