Metadata-Version: 2.1
Name: cool-booy-tmux
Version: 1.1.1
Summary: A tmux setup script for customizing tmux configurations.
Home-page: https://github.com/IM-COOL-HACKER-BOOY/cool-booy-tmux
Author: IM COOL BOOY
Author-email: coolbooy@gmail.com
Classifier: Programming Language :: Python :: 3
Classifier: License :: OSI Approved :: MIT License
Classifier: Operating System :: OS Independent
Requires-Python: >=3.6
License-File: LICENSE
Requires-Dist: colorama
